FlutterShizhan/README.md
FlutterShizhan/__init__.py
FlutterShizhan/__main__.py
FlutterShizhan/file.epub
FlutterShizhan/index.html
FlutterShizhan/css/__init__.py
FlutterShizhan/css/annotations.css
FlutterShizhan/css/main.css
FlutterShizhan/css/normalize.css
FlutterShizhan/css/popup.css
FlutterShizhan/font/__init__.py
FlutterShizhan/font/fontello.eot
FlutterShizhan/font/fontello.svg
FlutterShizhan/font/fontello.ttf
FlutterShizhan/font/fontello.woff
FlutterShizhan/img/__init__.py
FlutterShizhan/img/annotator-glyph-sprite.png
FlutterShizhan/img/annotator-icon-sprite.png
FlutterShizhan/img/apple-touch-icon.png
FlutterShizhan/img/cancelfullscreen.png
FlutterShizhan/img/close.png
FlutterShizhan/img/fullscreen.png
FlutterShizhan/img/loader.gif
FlutterShizhan/img/menu-icon.png
FlutterShizhan/img/save.png
FlutterShizhan/img/saved.png
FlutterShizhan/img/settings-s.png
FlutterShizhan/img/settings.png
FlutterShizhan/img/star.png
FlutterShizhan/js/__init__.py
FlutterShizhan/js/epub.js
FlutterShizhan/js/epub.min.js
FlutterShizhan/js/epub.min.map
FlutterShizhan/js/hooks.min.js
FlutterShizhan/js/hooks.min.map
FlutterShizhan/js/reader.js
FlutterShizhan/js/reader.js.map
FlutterShizhan/js/reader.min.js
FlutterShizhan/js/reader.min.map
FlutterShizhan/js/hooks/__init__.py
FlutterShizhan/js/hooks/extensions/__init__.py
FlutterShizhan/js/hooks/extensions/highlight.js
FlutterShizhan/js/libs/__init__.py
FlutterShizhan/js/libs/jquery.min.js
FlutterShizhan/js/libs/localforage.min.js
FlutterShizhan/js/libs/screenfull.js
FlutterShizhan/js/libs/screenfull.min.js
FlutterShizhan/js/libs/zip.min.js
FlutterShizhan/js/plugins/__init__.py
FlutterShizhan/js/plugins/hypothesis.js
FlutterShizhan/js/plugins/search.js
flutter_shizhan-2024.3.5.0.dist-info/METADATA
flutter_shizhan-2024.3.5.0.dist-info/WHEEL
flutter_shizhan-2024.3.5.0.dist-info/entry_points.txt
flutter_shizhan-2024.3.5.0.dist-info/top_level.txt
flutter_shizhan-2024.3.5.0.dist-info/RECORD
